non_normal/__init__.py
non_normal/fleishman.py
non_normal-0.1.2.dist-info/LICENSE
non_normal-0.1.2.dist-info/WHEEL
non_normal-0.1.2.dist-info/METADATA
non_normal-0.1.2.dist-info/RECORD
