Metadata-Version: 2.1
Name: non-normal
Version: 0.1.2
Summary: Generate non-normal distributions with known mean, variance, skewness and kurtosis
Home-page: https://github.com/<your-username>/hypermodern-python
License: MIT
Keywords: non-normal,fleishman,distribution,statistics
Author: Aman Chokshi
Author-email: achokshi@student.unimelb.edu.au
Requires-Python: >=3.9,<4.0
Classifier: License :: OSI Approved :: MIT License
Classifier: Programming Language :: Python :: 3
Classifier: Programming Language :: Python :: 3.9
Requires-Dist: numpy (>=1.25.0,<2.0.0)
Project-URL: Repository, https://github.com/<your-username>/hypermodern-python
